{
  "id": "0557aa1f0d02a91bce99d7b24adda42a",
  "title": "SVBPH Recruitment 2025 - Walk-in-Interview for 03 Senior Resident Post",
  "url": "https://allgovernmentjobs.in/svbph-recruitment-2025-walk-in-interview-for-03-senior-resident-post/34314",
  "source": "allgovernmentjobs.in",
  "description": "The Sardar Vallabh Bhai Patel Hospital (SVBPH) has announced the official notification for 2025. To fill up the vacancies for 03 Senior Resident Jobs. Those candidates who have qualified in the MBBS, Post-Graduation, or Diploma can grab this chance and apply for the SVBPH Recruitment 2025 . Here, we mentioned the age limit, selection process, salary structure, education details, application fee, and how to apply for these posts. Interested and eligible candidates can attend the interview at t...",
  "pdf_link": null,
  "important_dates": {
    "found_date": "26-08-2025"
  },
  "category": "Banking",
  "skills": [],
  "scraped_at": "2025-08-25T23:41:01.754779",
  "links": []
}