{
  "id": "0e152491eb493be769d167f936edd976",
  "title": "PGIMER Recruitment 2025 - Apply Online for Project Research Scientist Post",
  "url": "https://allgovernmentjobs.in/pgimer-recruitment-2025-apply-online-for-project-research-scientist-post/34162",
  "source": "allgovernmentjobs.in",
  "description": "Post Graduate Institute of Medical Education and Research, Chandigarh (PGIMER) has announced the official notification for 2025. To fill up the vacancies for Project Research Scientist Jobs. Those candidates who have qualified in the MBBS, BDS, and MVSc can grab this chance and apply for the PGIMER Recruitment 2025 . Here we included the age limit, selection process, salary structure, education details, application fee, and how to apply for these posts. Interested and eligible candidates can ...",
  "pdf_link": null,
  "important_dates": {
    "found_date": "14-08-2025"
  },
  "category": "Banking",
  "skills": [],
  "scraped_at": "2025-08-16T23:40:48.614081",
  "links": []
}