{
  "id": "11259c91f7ed65297c1e5d393ec94b65",
  "title": "Mizoram University Recruitment 2025 - Apply Online for 02 Guest Faculty Posts",
  "url": "https://allgovernmentjobs.in/mizoram-university-recruitment-2025-apply-online-for-02-guest-faculty-posts/35035",
  "source": "allgovernmentjobs.in",
  "description": "The Mizoram University has officially released the notification to fill the vacancies of 02 Guest Faculty Posts. Interested and eligible candidates can use this opportunity to apply for these posts before the last date of application. Candidates who have completed their M.E./M. Tech and MCA students can apply for the Mizoram University Recruitment 2025 . The interested applicants can apply in online mode. Here we have mentioned the education details, age limit, selection process, application ...",
  "pdf_link": null,
  "important_dates": {
    "last_date": "22-09-2025",
    "found_date": "11-09-2025"
  },
  "category": "Banking",
  "skills": [],
  "scraped_at": "2025-09-19T23:39:24.134144",
  "links": []
}