{
  "id": "1192b48c742781e3fc32aaeed8da74c7",
  "title": "VBU Notification 2026 - Apply Online for 26 Professor, Assistant Librarian Posts",
  "url": "https://allgovernmentjobs.in/vbu-notification-2026-apply-online-for-26-professor-assistant-librarian-posts/39953",
  "source": "allgovernmentjobs.in",
  "description": "The Visva Bharati University (VBU) has officially released the notification to fill the vacancies of 26 Professor, Assistant Professor, Associate Professor, and Assistant Librarian Jobs. Interested and eligibile candidates can use this opportunity to apply for these posts before the last date of application. Candidates who have completed their Post-graduation and  Ph.D. can apply for the VBU Notification 2026. The interested applicants can apply in online mode. Here we have mentioned the educ...",
  "pdf_link": null,
  "important_dates": {
    "last_date": "10-04-2026",
    "found_date": "11-03-2026"
  },
  "category": "Banking",
  "skills": [],
  "scraped_at": "2026-03-14T23:53:09.236090",
  "links": []
}