{
  "id": "14b86342d82d7a6657d6a98a4becdd28",
  "title": "JIPMER Recruitment 2026 - Apply Online for 110 Senior Resident Posts",
  "url": "https://allgovernmentjobs.in/jipmer-recruitment-2026-apply-online-for-110-senior-resident-posts/38469",
  "source": "allgovernmentjobs.in",
  "description": "Jawaharlal Institute of Postgraduate Medical Education and Research (JIPMER) has declared the official notification for 2026. To fill up vacancies for 110 Senior Resident Jobs. Those candidates who have qualified for the JIPMER Recruitment 2026 . Her,e we mentioned the age limit, selection process, salary structure, education details, application fee, and how to apply for these posts. Interested candidates can apply online before the last date of application. If you are looking for more, here...",
  "pdf_link": null,
  "important_dates": {
    "last_date": "03-02-2026",
    "found_date": "14-01-2026"
  },
  "category": "Banking",
  "skills": [
    "Data Entry"
  ],
  "scraped_at": "2026-01-16T23:44:04.032645",
  "links": []
}