{
  "id": "1507f0e704fd38a24265ad1e11f5b0aa",
  "title": "CGCRI Recruitment 2025 - Apply Offline for Project Associate Post",
  "url": "https://allgovernmentjobs.in/cgcri-recruitment-2025-apply-offline-for-project-associate-post/34134",
  "source": "allgovernmentjobs.in",
  "description": "Central Glass and Ceramic Research Institute (CGCRI) has announced the official notification for 2025. To fill up the vacancies for Project Associate Jobs. Those candidates who have qualified in the M.Sc., B.E/ B.Tech can grab this chance and apply for the CGCRI Recruitment 2025 . Here we include the age limit, selection process, salary structure, education details, application fee, and apply for these posts. Interested and eligible candidates can apply on or before the last date of applicati...",
  "pdf_link": null,
  "important_dates": {
    "found_date": "04-08-2025"
  },
  "category": "Banking",
  "skills": [
    "Analyst"
  ],
  "scraped_at": "2025-08-14T23:42:24.309395",
  "links": []
}