{
  "id": "1820d4aa20e3deca5289fbe6db340b20",
  "title": "AAI Pilot Recruitment 2025",
  "url": "https://www.rojgarresult.com/aai-pilot-recruitment/",
  "source": "www.rojgarresult.com",
  "description": "Airport Authority of India Pilot Recruitment 2025 Post Date: 06-06-2025 Short Description: AAI Pilot Recruitment 2025 : AAI Pilot Recruitment 2025 has been issued by Airport Authority of India This Recruitment has been issued on a Total of 02 Post , Candidate apply through offline mode within 04 June 2025 to 27 June 2025 . For more Information visit official website @https://www.aai.aero/. Candidate can download the official notification through the link given below.More Other Recruitment | J...",
  "pdf_link": null,
  "important_dates": {
    "found_date": "06-06-2025"
  },
  "category": "Banking",
  "skills": [
    "Mathematics"
  ],
  "scraped_at": "2025-09-30T23:39:26.189059",
  "links": [
    "https://www.aai.aero/",
    "https://www.aai.aero/."
  ]
}