{
  "id": "2905ac6b1227431d861640b4992cfdb6",
  "title": "Ministry of Tribal Affairs",
  "url": "https://allgovernmentjobs.in/ministry-of-tribal-affairs-recruitment",
  "source": "allgovernmentjobs.in",
  "description": "The Ministry of External Affairs announced the official notification for 2026. To fill up the vacancies for various&nbsp .... The Ministry of External Affairs has declared the official notification for 2025. To fill up the vacancies for Cons .... The Ministry of External Affairs has declared the official notification for 2025. To fill up the vacancies for Youn .... The Ministry of External Affairs has declared the official notification for 2025. To fill up the vacancies for Cons ....",
  "pdf_link": null,
  "important_dates": {},
  "category": "IT",
  "skills": [],
  "scraped_at": "2026-01-28T23:52:10.994103",
  "links": []
}