{
  "id": "489ebc1ebe2adcaa3a6e30efdc1bebaf",
  "title": "RGIPT Recruitment 2025 - Apply Offline for Junior Research Assistant Posts",
  "url": "https://allgovernmentjobs.in/rgipt-recruitment-2025-apply-offline-for-junior-research-assistant-posts/35030",
  "source": "allgovernmentjobs.in",
  "description": "The Rajiv Gandhi Institute of Petroleum Technology (RGIPT) has officially released the notification to fill the vacancies of 01 Junior Research Assistant Posts. Interested and eligible candidates can use this opportunity to apply for these posts before the last date of application. Candidates who have completed their M.Pharm, M.Sc, and B.E./B. Tech can apply for the RGIPT Recruitment 2025. The interested applicants can apply in offline mode. Here we have mentioned the education details, age l...",
  "pdf_link": null,
  "important_dates": {
    "last_date": "25-09-2025",
    "found_date": "18-09-2025"
  },
  "category": "Banking",
  "skills": [],
  "scraped_at": "2025-09-19T23:39:24.134249",
  "links": []
}