{
  "id": "52a3042918bfd391b48ac6f5328f4dbc",
  "title": "BFUHS",
  "url": "https://allgovernmentjobs.in/bfuhs-recruitment",
  "source": "allgovernmentjobs.in",
  "description": "Baba Farid University of Health Sciences (BFUHS) has declared the official notification for 2025. To fill up the vacanci .... The Baba Farid University of Health Sciences (BFUHS) has officially released the notification to fill the vacancies .... Baba Farid University of Health Science (BFUHS) has declared the latest job notification for 2025. To fill up the vacanc .... The Baba Farid University of Health Science (BFUHS) has declared the latest job notification for 2025. To fill up the va ......",
  "pdf_link": null,
  "important_dates": {},
  "category": "Medical",
  "skills": [],
  "scraped_at": "2025-11-20T23:41:08.951000",
  "links": []
}