{
  "id": "5324a3001be8b7e83d7a6262dd61b4d7",
  "title": "IMD Notification 2025 - Apply Online for 134 Scientific Assistant Posts",
  "url": "https://allgovernmentjobs.in/imd-notification-2025-apply-online-for-134-scientific-assistant-posts/36755",
  "source": "allgovernmentjobs.in",
  "description": "The India Meteorological Department (IMD) has officially released the notification to fill the vacancies of 134 Project Scientist I, II, III, E, Scientific Assistant, and Admin Assistant Jobs. Interested and eligibile candidates can use this opportunity to apply for these posts before the last date of application. Candidates who have completed their Any Degree, B.E./B. Tech, M.Sc., and M.E./M. Tech can apply for the IMD Notification 2025 . The interested applicants can apply in online mode. H...",
  "pdf_link": null,
  "important_dates": {
    "last_date": "14-12-2025",
    "found_date": "24-11-2025"
  },
  "category": "Banking",
  "skills": [],
  "scraped_at": "2025-11-15T23:40:19.443793",
  "links": []
}