{
  "id": "537439c8f2453b53faec8d80203c6ca0",
  "title": "UPPSC Assistant Prosecution Officer APO Online Form 2025 for 182 Post",
  "url": "https://www.rojgarresult.com/uppsc-apo-2025-for-182-post/",
  "source": "www.rojgarresult.com",
  "description": "UPPSC Assistant Prosecution Officer APO Recruitment 2025: Apply for 182 Post Post Date: 16-09-2025 Short Description: UPPSC Assistant Prosecution Officer APO Recruitment 2025 Apply Online Form : UPPSC Sahayak Abhiyojan Adhikari APO Online Form 2025, Notification has been released on the website @https://uppsc.up.nic.in/ & Application Form now started on 16 September 2025 to 16 October 2025. Uttar Pradesh Public Service Commission Jobs 2025. Get the direct link to download notification link av...",
  "pdf_link": null,
  "important_dates": {
    "found_date": "16-09-2025"
  },
  "category": "Banking",
  "skills": [
    "English",
    "Hindi"
  ],
  "scraped_at": "2025-09-16T23:40:22.609393",
  "links": [
    "https://uppsc.up.nic.in/"
  ]
}