{
  "id": "55596048298e9601bb238201761eae97",
  "title": "CCRH Notification 2026 - Walk - in interview for 05 Yoga Therapist Posts",
  "url": "https://allgovernmentjobs.in/ccrh-notification-2026-walk-in-interview-for-05-yoga-therapist-posts/42946",
  "source": "allgovernmentjobs.in",
  "description": "The Central Council for Research in Homoeopathy (CCRH) has officially released the notification to fill the vacancies of 05 Yoga Therapist Posts. Interested and eligibile candidates can use this opportunity to apply for these posts before the last date of application. Candidates who have completed their Any Degree and Diploma can apply for the CCRH Notification 2026 . The interested applicants can attend the walk-in interview. Here we have mentioned the education details, age limit, selection...",
  "pdf_link": null,
  "important_dates": {
    "last_date": "29-07-2026",
    "found_date": "25-06-2026"
  },
  "category": "Banking",
  "skills": [],
  "scraped_at": "2026-07-04T01:08:51.971221",
  "links": []
}