{
  "id": "55a30112cc1f3d2fa7257490c3f85f24",
  "title": "BIT Mersa Recruitment 2025 - Apply Offline for Assistant Professor Post",
  "url": "https://allgovernmentjobs.in/bit-mersa-recruitment-2025-apply-offline-for-assistant-professor-post/36159",
  "source": "allgovernmentjobs.in",
  "description": "Birla Institute of Technology Mesra (BIT Mesra) has declared the official notification for 2025. To fill up the vacancies for Assistant Professor Jobs. Those candidates who have qualified in the B.E/ B.Tech., M.E/ M.Tech. can grab this chance and apply for the BIT Mersa Recruitment 2025 . Here we include the age limit, selection process, salary structure, educational details, application fee, and how to apply for these posts. Interested and eligible candidates can apply on or before the last ...",
  "pdf_link": null,
  "important_dates": {
    "last_date": "04-11-2025",
    "found_date": "23-10-2025"
  },
  "category": "Banking",
  "skills": [
    "Data Entry"
  ],
  "scraped_at": "2025-10-28T23:40:50.283149",
  "links": []
}