{
  "id": "57f43d22799a34964f30417d6a2ec9f6",
  "title": "Bihar SHS ANM Online Form 2025 for 5006 Post",
  "url": "https://www.rojgarresult.com/bihar-shs-anm-2025/",
  "source": "www.rojgarresult.com",
  "description": "Bihar Swastha Vibhag ANM Recruitment 2025: Apply for 5006 Post Post Date: 14-08-2025 Short Description: Bihar SHS ANM Recruitment 2025 Apply Online Form : Bihar Swastha Vibhag SHS ANM Online Form 2025, Notification has been released on the website @https://shs.bihar.gov.in/ & Application Form now started on 14 August 2025 to 28 August 2025 for Total 5006 Post Bihar State Health Society Jobs 2025. Get the direct link to download notification link available on Bihar SHS ANM Vacancy 2025 Officia...",
  "pdf_link": null,
  "important_dates": {
    "found_date": "14-08-2025"
  },
  "category": "Banking",
  "skills": [],
  "scraped_at": "2025-08-14T23:42:49.210222",
  "links": [
    "https://shs.bihar.gov.in/"
  ]
}