{
  "id": "5a2d0f2b8e8a2f01f05c1200344498bb",
  "title": "Central Bank of India Jobs 2026 - Apply Online for 15 Assistant General Manager Posts",
  "url": "https://allgovernmentjobs.in/central-bank-of-india-jobs-2026-apply-online-for-15-assistant-general-manager-posts/41198",
  "source": "allgovernmentjobs.in",
  "description": "The Central Bank of India has officially released the notification to fill the vacancies of 15 Assistant General Manager Jobs. Interested and eligibile candidates can use this opportunity to apply for these posts before the last date of application. Candidates who have completed their Any Degree, Post-graduation, B.E./B. Tech in Computer Science Engineering, B.Sc., and MBA can apply for the Central Bank of India Jobs 2026 . The interested applicants can apply in online mode. Here we have ment...",
  "pdf_link": null,
  "important_dates": {
    "last_date": "17-05-2026",
    "found_date": "30-04-2026"
  },
  "category": "Banking",
  "skills": [
    "Data Entry"
  ],
  "scraped_at": "2026-05-01T00:15:38.800819",
  "links": []
}