{
  "id": "60d071f0ab1f8ef63582c608e797f2f2",
  "title": "CSIR NCL Notification 2026 - Apply Online for Project Associate I Posts",
  "url": "https://allgovernmentjobs.in/csir-ncl-notification-2026-apply-online-for-project-associate-i-posts/42720",
  "source": "allgovernmentjobs.in",
  "description": "CSIR National Chemical Laboratory (CSIR NCL) has published the official notification for the recruitment 2026. To fill up the vacancies for various Project Associate I Jobs. Candidates who have qualified in the M.Pharm, B.E/ B.Tech, M.V.Sc, and Post Graduation can use this chance and apply for the CSIR NCL Notification 2026 . Here, we included the age limit, selection process, salary structure, education details, application fee, and how to apply for these posts. Interested and eligible candi...",
  "pdf_link": null,
  "important_dates": {
    "found_date": "01-07-2026"
  },
  "category": "Banking",
  "skills": [],
  "scraped_at": "2026-06-23T01:31:08.770502",
  "links": []
}