{
  "id": "6d9519db9d0d547b9eee164f50fe352a",
  "title": "Latest Form 2025",
  "url": "https://www.rojgarresult.com/recruitments/",
  "source": "www.rojgarresult.com",
  "description": "Latest Form Online and Offline Form on Sarkari Naukri Result 2025, RojgarResults is a Latest Form  Recruitment Portal provides details of all Recruitment  , Sarkari Naukri 2025, rojgar result rojgarresult.com | Govt Jobs & Govt Jobs of Railway RRB NTPC,RRB Group D, 10 2 latest job. up police, bihar stet Latest Form Railway RRB Technician Online Form 2025 for 6238 Post UPPSC Assistant Teacher LT Online Form 2025 for 7466 Post RPSC Veterinary Officer Online Form 2025 for 1100 Post MHA IB Securi...",
  "pdf_link": null,
  "important_dates": {},
  "category": "Banking",
  "skills": [
    "Hindi"
  ],
  "scraped_at": "2025-07-28T19:21:50.368270",
  "links": []
}