{
  "id": "73b6bcdde4eee33070af10324a4934b7",
  "title": "IIT Gandhinagar Jobs 2026 - Apply Online for 02 Project Associate I Posts",
  "url": "https://allgovernmentjobs.in/iit-gandhinagar-jobs-2026-apply-online-for-02-project-associate-i-posts/41795",
  "source": "allgovernmentjobs.in",
  "description": "The Indian Institute of Technology Gandhinagar (IIT Gandhinagar) has officially released the notification to fill the vacancies of 02 Project Associate I Posts. Interested and eligibile candidates can use this opportunity to apply for these posts before the last date of application. Candidates who have completed their B.E./B. Tech, B.Sc., M.Sc. can apply for the IIT Gandhinagar Jobs 2026 . The interested applicants can apply in online mode. Here we have mentioned the education details, age li...",
  "pdf_link": null,
  "important_dates": {
    "last_date": "13-06-2026",
    "found_date": "21-05-2026"
  },
  "category": "Banking",
  "skills": [],
  "scraped_at": "2026-05-21T18:13:14.991143",
  "links": []
}