{
  "id": "85b36b3389f1df3719375e7e0d832c8c",
  "title": "Periyar University Notification 2026 - Apply Offline for Various Project Assistant Posts",
  "url": "https://allgovernmentjobs.in/periyar-university-notification-2026-apply-offline-for-various-project-assistant-posts/41828",
  "source": "allgovernmentjobs.in",
  "description": "Periyar University has declared the official notification for the recruitment of various  Project Assistant Jobs. Candidates who have qualified in the M.Sc can grab this chance and apply for the Periyar University Notification 2026 . Here, we provided more details about the age limit, selection process, salary structure, education details, application fee, and how to apply for these posts. Interested and eligible candidates can apply before the last date of application. If you are looking for...",
  "pdf_link": null,
  "important_dates": {
    "found_date": "25-05-2026"
  },
  "category": "Banking",
  "skills": [],
  "scraped_at": "2026-05-22T18:40:20.169760",
  "links": []
}