{
  "id": "8a84575996f0def58da552b77922a927",
  "title": "IIT Mandi Jobs 2026 - Apply Online for Junior Research Fellow Posts",
  "url": "https://allgovernmentjobs.in/iit-mandi-jobs-2026-apply-online-for-junior-research-fellow-posts/38558",
  "source": "allgovernmentjobs.in",
  "description": "The Indian Institute of Technology, Mandi (IIT Mandi) has officially released the notification to fill the vacancies of 01 Junior Research Fellow Posts. Interested and eligibile candidates can use this opportunity to apply for these posts before the last date of application. Candidates who have completed their B.E./B. Tech in Civil Engineering can apply for the IIT Mandi Jobs 2026. The interested applicants can apply in online mode. Here we have mentioned the education details, age limit, sel...",
  "pdf_link": null,
  "important_dates": {
    "last_date": "08-02-2026",
    "found_date": "19-01-2026"
  },
  "category": "Banking",
  "skills": [],
  "scraped_at": "2026-01-20T23:46:52.679255",
  "links": []
}