{
  "id": "8c508c221c5dafca02e9e56beb34030d",
  "title": "IIM Bengaluru Recruitment 2025 - Apply Online for Post Doctoral Fellow Post",
  "url": "https://allgovernmentjobs.in/iim-bengaluru-recruitment-2025-apply-online-for-post-doctoral-fellow-post/34576",
  "source": "allgovernmentjobs.in",
  "description": "Indian Institute of Management (IIM) Bangalore has announced the official notification for 2025. To fill up the vacancies for Post-Doctoral Fellow Jobs. Those candidates who have qualified for the Ph.D can grab this chance and apply for the IIM Bengaluru Recruitment 2025 . Here, we include the age limit, selection process, salary structure, education details, application fee, and how to apply for these posts. Interested and eligible candidates can apply online through the website on or before...",
  "pdf_link": null,
  "important_dates": {
    "found_date": "01-09-2025"
  },
  "category": "Banking",
  "skills": [
    "Word"
  ],
  "scraped_at": "2025-09-03T23:38:46.597147",
  "links": []
}