{
  "id": "91710726b44f5a0a28c1214dd6bda981",
  "title": "ACTREC Recruitment 2026 - Walk-in-Interview for Clinical Trial Coordinator Posts",
  "url": "https://allgovernmentjobs.in/actrec-recruitment-2026-walk-in-interview-for-clinical-trial-coordinator-posts/38949",
  "source": "allgovernmentjobs.in",
  "description": "The Advanced Centre for Treatment Research and Education in Cancer (ACTREC) has published the official notification for 2026. To fill up the vacancies for Clinical Trial Coordinator Jobs. Those candidates who have qualified in the Post Graduation, M.Pharm, can grab this chance and apply for the ACTREC Recruitment 2026 . Here, we mentioned more information about the age limit, selection process, salary structure, education details, application fee, and how to apply for these posts. Interested ...",
  "pdf_link": null,
  "important_dates": {
    "found_date": "12-02-2026"
  },
  "category": "Banking",
  "skills": [],
  "scraped_at": "2026-02-05T23:51:13.279613",
  "links": []
}