{
  "id": "949910432190f60e82f2170e33f0ed95",
  "title": "IIT Kanpur",
  "url": "https://allgovernmentjobs.in/iit-kanpur-recruitment",
  "source": "allgovernmentjobs.in",
  "description": "Indian Institute of Technology Kanpur (IIT Kanpur)  has released an official notification for the recruitment of va .... Indian Institute of Technology Kanpur (IIT Kanpur)  has released an official notification for the recruitment of Pr .... The Indian Institute of Technology Kanpur (IIT Kanpur) has officially released the notification to fill the vacancies of .... Indian Institute of Technology Kanpur (IIT Kanpur) has declared the official notification for 2026. Allotted various vac .... The...",
  "pdf_link": null,
  "important_dates": {},
  "category": "Engineering",
  "skills": [],
  "scraped_at": "2026-02-18T23:55:20.667824",
  "links": []
}