{
  "id": "949ac19ee21c4b1f410ee916794cde08",
  "title": "Sainik School Tilaiya Recruitment 2025 - Apply Offline for 02 Lower Division Clerk and Ward Boy Posts",
  "url": "https://allgovernmentjobs.in/sainik-school-tilaiya-recruitment-2025-apply-offline-for-02-lower-division-clerk-and-ward-boy-posts/33860",
  "source": "allgovernmentjobs.in",
  "description": "The Sainik School Tilaiya has announced the official notification for 2025. To fill up the vacancies for Lower Division Clerk and Ward Boy Jobs. Those candidates who have qualified in the 10th Pass can grab this chance and apply for these posts. Here, we include the age limit, selection process, salary structure, education details, application fee, and how to apply for the Sainik School Tilaiya Recruitment 2025 . Interested and eligible candidates can apply on or before the last date of appli...",
  "pdf_link": null,
  "important_dates": {
    "found_date": "01-08-2025"
  },
  "category": "Banking",
  "skills": [],
  "scraped_at": "2025-08-02T23:46:45.667703",
  "links": []
}