{
  "id": "9a312ba058b8d1c4fae0d1340a3e06a6",
  "title": "CG Vyapam Recruitment 2025 - Apply Online for 50 Handpump Technician Posts",
  "url": "https://allgovernmentjobs.in/cg-vyapam-recruitment-2025-apply-online-for-50-handpump-technician-posts/35072",
  "source": "allgovernmentjobs.in",
  "description": "The Chhattisgarh Vyavasayil Pariksha Mandal (CG Vyapam) has officially released the notification to fill the vacancies of 50 Handpump Technician Posts. Interested and eligible candidates can use this opportunity to apply for these posts before the last date of application. Candidates who have completed their 12th and ITI can apply for the CG Vyapam Recruitment 2025 . The interseted applicants can apply in online mode. Here we have mentioned the education details, age limit, selection process,...",
  "pdf_link": null,
  "important_dates": {
    "last_date": "10-10-2025",
    "found_date": "18-09-2025"
  },
  "category": "Banking",
  "skills": [],
  "scraped_at": "2025-09-20T23:39:01.547224",
  "links": []
}