{
  "id": "9f785a4bdc0607a77af10f7dba6f9044",
  "title": "B.Tech / MBA Jobs",
  "url": "https://www.rojgarresult.com/category/btech-mba/",
  "source": "www.rojgarresult.com",
  "description": "Skip to content Rojgar Result | RojgarResult.Com Menu Home Latest Result 2025 Admit Card Answer Key Admission Latest Form 2025 About Us Contact Us Privacy Policy Rojgar Result RojgarResult.Com Rojgar Result | RojgarResult.Com Menu Home Latest Result 2025 Admit Card Answer Key Admission Latest Form 2025 About Us Contact Us Privacy Policy Rojgar Result RojgarResult.Com > B.Tech MBA Jobs August 28, 2025 AAI Junior Executive Online Form 2025 for 976 Post August 25, 2025 Bihar BSSC 4th Graduate Le...",
  "pdf_link": null,
  "important_dates": {},
  "category": "Banking",
  "skills": [
    "Hindi"
  ],
  "scraped_at": "2025-08-29T23:39:58.566590",
  "links": []
}