{
  "id": "a39b5aaa16820aeb183b68db3358a932",
  "title": "BFUHS Notification 2026 - Apply Offline for Junior Pharmacovigilance Associate Posts",
  "url": "https://allgovernmentjobs.in/bfuhs-notification-2026-apply-offline-for-junior-pharmacovigilance-associate-posts/38906",
  "source": "allgovernmentjobs.in",
  "description": "The Baba Farid University of Health Science (BFUHS) has officially released the notification to fill the vacancies of 01 Junior Pharmacovigilance Associate Posts. Interested and eligibile candidates can use this opportunity to apply for these posts before the last date of application. Candidates who have completed their MBBS, BDS, and Pharm D can apply for the BFUHS Notification 2026. The interested applicants can apply in offline mode. Here we have mentioned the education details, age limit,...",
  "pdf_link": null,
  "important_dates": {
    "last_date": "06-02-2026",
    "found_date": "31-01-2026"
  },
  "category": "Banking",
  "skills": [],
  "scraped_at": "2026-02-04T23:53:31.129685",
  "links": []
}