{
  "id": "a570abca9c278889d7648f58c06af115",
  "title": "ACTREC Notification 2026 - Walk-in interview for Assistant Research Fellow Posts",
  "url": "https://allgovernmentjobs.in/actrec-notification-2026-walk-in-interview-for-assistant-research-fellow-posts/42778",
  "source": "allgovernmentjobs.in",
  "description": "The Advanced Centre for Treatment Research and Education in Cancer (ACTREC) has officially released the notification to fill the vacancies of 01 Assistant Research Fellow Posts. Interested and eligibile candidates can use this opportunity to apply for these posts before the last date of application. Candidates who have completed their BDS, BAMS, PGDM, Pharm D can apply for the ACTREC Notification 2026 . The interested applicants can attend the walk-in interview. Here we have mentioned the edu...",
  "pdf_link": null,
  "important_dates": {
    "last_date": "07-07-2026",
    "found_date": "22-06-2026"
  },
  "category": "Banking",
  "skills": [],
  "scraped_at": "2026-06-26T01:38:27.470621",
  "links": []
}