{
  "id": "ad94ce9f16353c50f4dbb33ab37454ff",
  "title": "MPPSC State Service Exam SSE Pre 2026 Online Form | Syllabus",
  "url": "https://www.rojgarresult.com/mppsc-sse-pre-2026/",
  "source": "www.rojgarresult.com",
  "description": "MPPSC State Service Exam SSE MP PSC Pre 2026 : Apply Online for 155 Post Post Update Date: 08-01-2026 Short Description: MPPSC State Service Exam SSE 2026 : Madhya Pradesh Public Service Commission (MPPSC) has released the notification for State Service Examination (SSE) 2026 . Online application process will start from 10 January 2026 and the last date for registration and fee payment is 09 February 2026 . Candidates can also apply with late fee in two phases. MPPSC SSE Preliminary Examinati...",
  "pdf_link": null,
  "important_dates": {
    "last_date": "01/04/2026",
    "found_date": "08-01-2026"
  },
  "category": "Banking",
  "skills": [],
  "scraped_at": "2026-01-08T23:43:04.212924",
  "links": []
}