{
  "id": "b44a95488a0ceec085c4584d03ec59a0",
  "title": "NIT Jalandhar",
  "url": "https://allgovernmentjobs.in/nit-jalandhar-recruitment",
  "source": "allgovernmentjobs.in",
  "description": "The National Institute of Technology Jalandhar (NIT Jalandhar) has officially released the notification to fill the vaca .... National Institute of Technology Jalandhar (NIT Jalandhar) has declared the official notification for 2026. To fill up t .... National Institute of Technology Jalandhar (NIT Jalandhar) has declared the official notification for 2026. To fill up t .... National Institute of Technology Jalandhar (NIT Jalandhar) has declared the official notification for 2026. To fill up ...",
  "pdf_link": null,
  "important_dates": {},
  "category": "IT",
  "skills": [],
  "scraped_at": "2026-04-28T00:13:58.913398",
  "links": []
}