{
  "id": "bac63a693ad415c38ed15f843d9780c2",
  "title": "IIT Gandhinagar Recruitment 2026 - Apply Online for Post Doctoral Fellow Posts",
  "url": "https://allgovernmentjobs.in/iit-gandhinagar-recruitment-2026-apply-online-for-post-doctoral-fellow-posts/41797",
  "source": "allgovernmentjobs.in",
  "description": "Indian Institute of Technology Gandhinagar (IIT Gandhinagar) has officially released the notification for 2026. Allotted various vacancies for Post-Doctoral Fellow Jobs. Candidates who have qualified for a Ph.D. can grab this chance and apply for the IIT Gandhinagar Recruitment 2026 . Here, we included the age limit, selection process, salary structure, education details, application fee, and how to apply for these posts. Interested and eligible candidates can apply before the last date of ap...",
  "pdf_link": null,
  "important_dates": {
    "found_date": "02-06-2026"
  },
  "category": "Banking",
  "skills": [],
  "scraped_at": "2026-05-21T18:13:14.985055",
  "links": []
}