{
  "id": "cd60997d3c96177f7c275afa6e376d47",
  "title": "10th & 10+2 Jobs",
  "url": "https://www.rojgarresult.com/category/10th-12th/",
  "source": "www.rojgarresult.com",
  "description": "Skip to content Rojgar Result | RojgarResult.Com Menu Home Latest Result 2025 Admit Card Answer Key Admission Latest Form 2025 About Us Contact Us Privacy Policy Rojgar Result RojgarResult.Com Rojgar Result | RojgarResult.Com Menu Home Latest Result 2025 Admit Card Answer Key Admission Latest Form 2025 About Us Contact Us Privacy Policy Rojgar Result RojgarResult.Com > 10th 12th Jobs January 13, 2026 UP Police Constable Online Form 2026 for 32679 Post January 13, 2026 IAF Indian Air Force Air...",
  "pdf_link": null,
  "important_dates": {},
  "category": "Banking",
  "skills": [],
  "scraped_at": "2026-01-13T23:42:52.448376",
  "links": []
}