{
  "id": "d0a09af8efbd496b807ddb52ce816b87",
  "title": "IRCTC Notification 2026 - Apply for Group General Manager Posts",
  "url": "https://allgovernmentjobs.in/irctc-notification-2026-apply-for-group-general-manager-posts/40990",
  "source": "allgovernmentjobs.in",
  "description": "Indian Railway Catering and Tourism Corporation (IRCTC) has declared the official notification for 2026. To fill up the vacancies for Group General Manager Jobs. Those candidates who have qualified for any degree can grab this chance and apply for the IRCTC Notification 2026 . Here, we included more details on the age limit, selection process, salary structure, education details, application fee, and how to apply for these posts. If you are looking for more, here is a list of Government Jobs ...",
  "pdf_link": null,
  "important_dates": {
    "found_date": "02-05-2026"
  },
  "category": "Banking",
  "skills": [
    "Data Entry"
  ],
  "scraped_at": "2026-04-24T00:09:54.044472",
  "links": []
}