{
  "id": "d4dad79cf4639b90820476167f7b96c4",
  "title": "Ministry of External Affairs Recruitment 2025 - Apply Offline for Young Professional Post",
  "url": "https://allgovernmentjobs.in/ministry-of-external-affairs-recruitment-2025-apply-offline-for-young-professional-post/35530",
  "source": "allgovernmentjobs.in",
  "description": "The Ministry of External Affairs has declared the official notification for 2025. To fill up the vacancies for Young Professional Jobs. Those candidates who have qualified in Any Degree can grab this chance and apply for the Ministry of External Affairs Recruitment 2025 . Here, we mentioned the age limit, selection process, salary structure, education details, application fee, and how to apply for these posts. Interested and eligible candidates can apply on or before the last date of applicat...",
  "pdf_link": null,
  "important_dates": {
    "last_date": "23-10-2025",
    "found_date": "03-10-2025"
  },
  "category": "Banking",
  "skills": [
    "Data Entry"
  ],
  "scraped_at": "2025-10-07T23:39:07.759173",
  "links": []
}