{
  "id": "d6bd0bd678c57281dd6b1ba160fbd783",
  "title": "DHS Dahod Recruitment 2025 - Apply Online for 27 Community Health Officer Posts",
  "url": "https://allgovernmentjobs.in/dhs-dahod-recruitment-2025-apply-online-for-27-community-health-officer-posts/34100",
  "source": "allgovernmentjobs.in",
  "description": "The District Health Society Dahod (DHS Dahod) has officially released the notification to fill the vacancies of 27 Community Health Officers, Medical Officers, and Audiologist Posts. Interested and eligible candidates can use this opportunity to apply for these posts before the last date of application. Candidates who have completed their GNM, B.Sc Nursing, MBBS, BAMS, B.Sc, and Any Degree can apply for the DHS Dahod Recruitment 2025. The interested applicants can apply in online mode. Here w...",
  "pdf_link": null,
  "important_dates": {
    "last_date": "23-08-2025",
    "found_date": "13-08-2025"
  },
  "category": "Banking",
  "skills": [],
  "scraped_at": "2025-08-13T23:42:27.522268",
  "links": []
}