{
  "id": "db9a70d43d60266db1fb9286b592402d",
  "title": "TGPSC Notification 2026 - Apply Online for 19 Assistant Environmental Engineer Posts",
  "url": "https://allgovernmentjobs.in/tgpsc-notification-2026-apply-online-for-19-assistant-environmental-engineer-posts/42119",
  "source": "allgovernmentjobs.in",
  "description": "The Telangana Public Service Commission, Hyderabad (IIT Hyderabad), has officially released the notification to fill the vacancies of 19 Assistant Environmental Engineer Jobs. Interested and eligibile candidates can use this opportunity to apply for these posts before the last date of application. Candidates who have completed their B.E./B. Tech in Mechanical and Civil Engineering can apply for the TGPSC Notification 2026 . The interested applicants can apply in online mode. Here we have ment...",
  "pdf_link": null,
  "important_dates": {
    "last_date": "17-07-2026",
    "found_date": "02-06-2026"
  },
  "category": "Banking",
  "skills": [],
  "scraped_at": "2026-06-05T01:37:53.155588",
  "links": []
}