{
  "id": "e0a79962c29b53b16b7e22605550ba8e",
  "title": "NMMC Recruitment 2025 - Apply Offline for 06 TBHV, Medical Officer Posts",
  "url": "https://allgovernmentjobs.in/nmmc-recruitment-2025-apply-offline-for-06-tbhv-medical-officer-posts/35783",
  "source": "allgovernmentjobs.in",
  "description": "The Navi Mumbai Municipal Corporation (NMMC) has officially released the notification to fill the vacancies of 06 Medical Officers, Supervisors, and TB Health Visitor Jobs. Interested and eligible candidates can use this opportunity to apply for these posts before the last date of application. Candidates who have completed their MBBS, Any Degree, B.E./B. Tech, 12th, Diploma, DMLT, MD/MS, and ANM can apply for the NMMC Recruitment 2025 . The interested applicants can apply in offline mode. Her...",
  "pdf_link": null,
  "important_dates": {
    "last_date": "31-10-2025",
    "found_date": "14-10-2025"
  },
  "category": "Banking",
  "skills": [],
  "scraped_at": "2025-10-14T23:39:08.510760",
  "links": []
}