{
  "id": "f8c70b06e0b80d594fcaddfda077c9a3",
  "title": "NMC Recruitment 2025 - Walk-in-Interview for 20 Secondary Teacher Posts",
  "url": "https://allgovernmentjobs.in/nmc-recruitment-2025-walk-in-interview-for-20-secondary-teacher-posts/33989",
  "source": "allgovernmentjobs.in",
  "description": "The Nagpur Municipal Corporation (NMC) has announced the official notification for 2025. To fill up the vacancies for 20 Teacher Jobs. Those candidates who have qualified in Any Degree, B.Ed, or B.Sc can apply for the NMC Recruitment 2025 . Here, we include the age limit, selection process, salary structure, education details, application fee, and how to apply for these posts. Interested and eligible candidates can attend the walk-in interview along with the documents required to the address ...",
  "pdf_link": null,
  "important_dates": {},
  "category": "Banking",
  "skills": [
    "Analyst"
  ],
  "scraped_at": "2025-08-08T23:43:42.829240",
  "links": []
}