{
  "id": "fd579d032265cc556d3acae14b43f76e",
  "title": "ANGRAU Notification 2026 - Walk-in-Interview for Teaching Assistant Posts",
  "url": "https://allgovernmentjobs.in/angrau-notification-2026-walk-in-interview-for-teaching-assistant-posts/39326",
  "source": "allgovernmentjobs.in",
  "description": "Acharya NG Ranga Agricultural University (ANGRAU) has declared the official notification for 2026. To fill up the various vacancies for Teaching Assistant Jobs. Candidates who have qualified in Any Degree, post-graduation, and Ph.D can use this opportunity and apply for the ANGRAU Notification 2026 . Here we include the age limit, selection process, and salary structure, education aldetails, application fee, and how to apply for these posts. If you are looking for more, here is a list of Gove...",
  "pdf_link": null,
  "important_dates": {
    "found_date": "02-03-2026"
  },
  "category": "Banking",
  "skills": [
    "English"
  ],
  "scraped_at": "2026-02-23T23:55:13.890665",
  "links": []
}